CMakeLists.txt
README.md
pyproject.toml
setup.py
TheengsDecoder/__init__.py
TheengsDecoder/_decoder.cpp
src/decoder.cpp
src/decoder.h
src/decoder_c.cpp
src/devices.h
src/arduino_json/.clang-format
src/arduino_json/.git
src/arduino_json/.gitattributes
src/arduino_json/.gitignore
src/arduino_json/.mbedignore
src/arduino_json/.prettierignore
src/arduino_json/ArduinoJson.h
src/arduino_json/CHANGELOG.md
src/arduino_json/CMakeLists.txt
src/arduino_json/CONTRIBUTING.md
src/arduino_json/LICENSE.md
src/arduino_json/README.md
src/arduino_json/SUPPORT.md
src/arduino_json/appveyor.yml
src/arduino_json/banner.svg
src/arduino_json/component.mk
src/arduino_json/keywords.txt
src/arduino_json/library.json
src/arduino_json/library.properties
src/arduino_json/.devcontainer/Dockerfile
src/arduino_json/.devcontainer/devcontainer.json
src/arduino_json/.github/FUNDING.yml
src/arduino_json/.github/ISSUE_TEMPLATE.md
src/arduino_json/.github/workflows/ci.yml
src/arduino_json/.github/workflows/lock.yml
src/arduino_json/.github/workflows/release.yml
src/arduino_json/.vscode/settings.json
src/arduino_json/examples/JsonConfigFile/JsonConfigFile.ino
src/arduino_json/examples/JsonFilterExample/JsonFilterExample.ino
src/arduino_json/examples/JsonGeneratorExample/JsonGeneratorExample.ino
src/arduino_json/examples/JsonHttpClient/JsonHttpClient.ino
src/arduino_json/examples/JsonParserExample/JsonParserExample.ino
src/arduino_json/examples/JsonServer/JsonServer.ino
src/arduino_json/examples/JsonUdpBeacon/JsonUdpBeacon.ino
src/arduino_json/examples/MsgPackParser/MsgPackParser.ino
src/arduino_json/examples/ProgmemExample/ProgmemExample.ino
src/arduino_json/examples/StringExample/StringExample.ino
src/arduino_json/extras/ArduinoJsonConfig.cmake.in
src/arduino_json/extras/CompileOptions.cmake
src/arduino_json/extras/ci/arduino.sh
src/arduino_json/extras/ci/particle.sh
src/arduino_json/extras/ci/espidf/CMakeLists.txt
src/arduino_json/extras/ci/espidf/main/CMakeLists.txt
theengsdecoder.egg-info/PKG-INFO
theengsdecoder.egg-info/SOURCES.txt
theengsdecoder.egg-info/dependency_links.txt
theengsdecoder.egg-info/top_level.txt