Metadata-Version: 2.1
Name: theengsdecoder
Version: 2.0.0
Summary: A message decoder for the Internet of Things
Author: Theengs
License:  GPL-3.0 License
